netrd/__init__.py
netrd/distance/__init__.py
netrd/distance/base.py
netrd/distance/communicability_jsd.py
netrd/distance/degree_divergence.py
netrd/distance/deltacon.py
netrd/distance/distributional_nbd.py
netrd/distance/dk_series.py
netrd/distance/dmeasure.py
netrd/distance/frobenius.py
netrd/distance/graph_diffusion.py
netrd/distance/hamming.py
netrd/distance/hamming_ipsen_mikhailov.py
netrd/distance/ipsen_mikhailov.py
netrd/distance/jaccard_distance.py
netrd/distance/laplacian_spectral_method.py
netrd/distance/nbd.py
netrd/distance/netlsd.py
netrd/distance/netsimile.py
netrd/distance/onion_divergence.py
netrd/distance/polynomial_dissimilarity.py
netrd/distance/portrait_divergence.py
netrd/distance/quantum_jsd.py
netrd/distance/resistance_perturbation.py
netrd/dynamics/SIS.py
netrd/dynamics/__init__.py
netrd/dynamics/base.py
netrd/dynamics/branching_process.py
netrd/dynamics/ising_glauber.py
netrd/dynamics/kuramoto.py
netrd/dynamics/lotka_volterra.py
netrd/dynamics/sherrington_kirkpatrick.py
netrd/dynamics/single_unbiased_random_walker.py
netrd/dynamics/voter.py
netrd/reconstruction/__init__.py
netrd/reconstruction/base.py
netrd/reconstruction/convergent_cross_mapping.py
netrd/reconstruction/correlation_matrix.py
netrd/reconstruction/correlation_spanning_tree.py
netrd/reconstruction/free_energy_minimization.py
netrd/reconstruction/granger_causality.py
netrd/reconstruction/graphical_lasso.py
netrd/reconstruction/marchenko_pastur.py
netrd/reconstruction/maximum_likelihood_estimation.py
netrd/reconstruction/mean_field.py
netrd/reconstruction/mutual_information_matrix.py
netrd/reconstruction/naive_transfer_entropy.py
netrd/reconstruction/optimal_causation_entropy.py
netrd/reconstruction/ou_inference.py
netrd/reconstruction/partial_correlation_influence.py
netrd/reconstruction/partial_correlation_matrix.py
netrd/reconstruction/random.py
netrd/reconstruction/thouless_anderson_palmer.py
netrd/reconstruction/time_granger_causality.py
netrd/utilities/__init__.py
netrd-0.3.0.dist-info/LICENSE
netrd-0.3.0.dist-info/METADATA
netrd-0.3.0.dist-info/WHEEL
netrd-0.3.0.dist-info/top_level.txt
netrd-0.3.0.dist-info/RECORD
